LICENSE.md
README.md
pyproject.toml
setup.py
convokit/__init__.py
convokit/convokitConfig.py
convokit/convokitPipeline.py
convokit/transformer.py
convokit/util.py
convokit.egg-info/PKG-INFO
convokit.egg-info/SOURCES.txt
convokit.egg-info/dependency_links.txt
convokit.egg-info/requires.txt
convokit.egg-info/top_level.txt
convokit/bag_of_words/__init__.py
convokit/bag_of_words/bow_transformer.py
convokit/classifier/__init__.py
convokit/classifier/classifier.py
convokit/classifier/classifierModel.py
convokit/classifier/util.py
convokit/classifier/vectorClassifier.py
convokit/convo_similarity/__init__.py
convokit/convo_similarity/baseline.py
convokit/convo_similarity/condyns.py
convokit/convo_similarity/naive_condyns.py
convokit/convo_similarity/scd.py
convokit/convo_similarity/utils.py
convokit/convo_similarity/prompts/condyns_prompt.txt
convokit/convo_similarity/prompts/naive_condyns_prompt.txt
convokit/convo_similarity/prompts/scd_prompt.txt
convokit/convo_similarity/prompts/sop_prompt.txt
convokit/coordination/__init__.py
convokit/coordination/coordination.py
convokit/coordination/coordinationScore.py
convokit/data/coord-liwc-patterns.txt
convokit/data/liu-negative-words.txt
convokit/data/liu-positive-words.txt
convokit/expected_context_framework/__init__.py
convokit/expected_context_framework/col_normed_tfidf.py
convokit/expected_context_framework/dual_context_wrapper.py
convokit/expected_context_framework/expected_context_model.py
convokit/expected_context_framework/expected_context_model_pipeline.py
convokit/fighting_words/__init__.py
convokit/fighting_words/fightingWords.py
convokit/forecaster/CRAFTModel.py
convokit/forecaster/TransformerDecoderModel.py
convokit/forecaster/TransformerEncoderModel.py
convokit/forecaster/TransformerForecasterConfig.py
convokit/forecaster/__init__.py
convokit/forecaster/cumulativeBoW.py
convokit/forecaster/forecaster.py
convokit/forecaster/forecasterModel.py
convokit/forecaster/CRAFT/__init__.py
convokit/forecaster/CRAFT/data.py
convokit/forecaster/CRAFT/model.py
convokit/forecaster/CRAFT/runners.py
convokit/genai/__init__.py
convokit/genai/base.py
convokit/genai/factory.py
