Metadata-Version: 2.4
Name: convokit
Version: 4.0.0
Summary: ConvoKit
Home-page: https://github.com/CornellNLP/ConvoKit
Author: Jonathan P. Chang, Caleb Chiam, Liye Fu, Andrew Wang, Justine Zhang, Cristian Danescu-Niculescu-Mizil
Author-email: cristian@cs.cornell.edu
Classifier: Programming Language :: Python
Classifier: Programming Language :: Python :: 3.10
Classifier: Programming Language :: Python :: 3.11
Classifier: Programming Language :: Python :: 3.12
License-File: LICENSE.md
Requires-Dist: matplotlib>=3.0.0
Requires-Dist: scipy>1.14
Requires-Dist: pandas>=1.5.0
Requires-Dist: numpy>=2.0.0
Requires-Dist: msgpack-numpy>=0.4.3.2
Requires-Dist: spacy>=3.8.2
Requires-Dist: scikit-learn>=1.0
Requires-Dist: nltk>=3.4
Requires-Dist: dill>=0.2.9
Requires-Dist: joblib>=0.13.2
Requires-Dist: clean-text>=0.6.0
Requires-Dist: unidecode>=1.1.1
Requires-Dist: tqdm>=4.64.0
Requires-Dist: pymongo>=4.0
Requires-Dist: pyyaml>=5.4.1
Requires-Dist: dnspython>=1.16.0
Requires-Dist: thinc<8.4.0,>=8.3.0
Requires-Dist: h5py==3.12.1
Requires-Dist: numexpr>=2.8.0
Requires-Dist: ruff>=0.4.8
Requires-Dist: bottleneck
Requires-Dist: accelerate
Requires-Dist: peft
Requires-Dist: bitsandbytes
Requires-Dist: transformers
Requires-Dist: unsloth
Requires-Dist: trl>=0.12.2
Requires-Dist: tensorflow>=2.18.0
Requires-Dist: tf-keras<3.0.0,>=2.17.0
Requires-Dist: evaluate
Requires-Dist: sentence-transformers
Requires-Dist: datasets
Provides-Extra: craft
Requires-Dist: torch>=0.12; extra == "craft"
Provides-Extra: forecaster
Requires-Dist: torch>=0.12; extra == "forecaster"
Requires-Dist: datasets; extra == "forecaster"
Provides-Extra: genai
Requires-Dist: openai>=1.3.5; extra == "genai"
Requires-Dist: google-genai; extra == "genai"
Provides-Extra: llm
Requires-Dist: torch>=0.12; extra == "llm"
Requires-Dist: accelerate; extra == "llm"
Requires-Dist: peft; extra == "llm"
Requires-Dist: bitsandbytes; extra == "llm"
Requires-Dist: transformers; extra == "llm"
Requires-Dist: unsloth; extra == "llm"
Requires-Dist: trl>=0.12.2; extra == "llm"
Requires-Dist: tensorflow>=2.18.0; extra == "llm"
Requires-Dist: tf-keras<3.0.0,>=2.17.0; extra == "llm"
Dynamic: author
Dynamic: author-email
Dynamic: classifier
Dynamic: home-page
Dynamic: license-file
Dynamic: provides-extra
Dynamic: requires-dist
Dynamic: summary
